{
  "HotzingTone": [
    "ebyau",
    "keting-ai"
  ],
  "1Doomdie1": [
    "ZeynelAbidin91",
    "SayanJerr"
  ],
  "Ishticode": [
    "Husain-Ayoob",
    "sohil-hub"
  ],
  "bicycleman15": [
    "fmilheir",
    "bethelhall"
  ],
  "mattbarrett98": [
    "DhruvaBhardwaj404",
    "RickSanchezStoic"
  ],
  "saeedashrraf": [
    "kirodev",
    "uchennayah"
  ],
  "sherry30": [
    "RitujaPawas",
    "sreegandh804"
  ],
  "vedpatwardhan": [
    "zaeemansari70",
    "Aarsh2001"
  ],
  "RashulChutani": [
    "arv0804"
  ],
  "Darshan-H-E": [
    "AnimeshGurjar"
  ]
}
